django_graylog/__init__.py
django_graylog-0.8.0.dist-info/WHEEL
django_graylog-0.8.0.dist-info/METADATA
django_graylog-0.8.0.dist-info/RECORD
