Metadata-Version: 2.3
Name: django-graylog
Version: 0.8.0
Summary: Graylog middleware for Django.
Author: Dan Watson
Author-email: Dan Watson <watsond@imsweb.com>
License: MIT
Classifier: Development Status :: 4 - Beta
Classifier: Intended Audience :: Developers
Classifier: License :: OSI Approved :: MIT License
Classifier: Programming Language :: Python
Classifier: Programming Language :: Python :: 3
Classifier: Topic :: System :: Logging
Classifier: Topic :: System :: Monitoring
Requires-Dist: requests ; extra == 'all'
Requires-Dist: ua-parser ; extra == 'all'
Requires-Dist: requests ; extra == 'http'
Requires-Dist: ua-parser ; extra == 'ua'
Requires-Python: >=3.10
Project-URL: Homepage, https://github.com/imsweb/django-graylog
Provides-Extra: all
Provides-Extra: http
Provides-Extra: ua
